Workbook
Name TaxRate: Assumptions!$B$14

Sheet Assumptions
A1: Northwind Coffee: 5-year plan
A3: Assumption | B3: Value | C3: Notes
A4: Price per cup (2027) | B4: 4.6 | C4: Average ticket ÷ cups
A5: Cups per store per day | B5: 310 | C5: From the pilot store
A6: Days open per year | B6: 360
A7: Price increase per year | B7: 0.03
A8: Cost of goods (% of sales) | B8: 0.31 | C8: Beans, milk, cups
A9: Rent per store per year | B9: 84000
A10: Staff per store | B10: 6
A11: Salary per staff member | B11: 38000 | C11: Fully loaded
A12: Marketing (% of sales) | B12: 0.05 | C12: Agreed with the board in March
A13: Opening cost per new store | B13: 250000 | C13: Fit-out and equipment
A14: Tax rate | B14: 0.25
A16: Stores open (end of year) | C16: 2027 | D16: 2028 | E16: 2029 | F16: 2030 | G16: 2031
A17: Stores | C17: 4 | D17: 6 | E17: 9 | F17: 12 | G17: 15

Sheet Revenue
A1: Revenue
C3: 2027 | D3: =C3+1 -> 2028 | E3: =D3+1 -> 2029 | F3: =E3+1 -> 2030 | G3: =F3+1 -> 2031
A4: Stores | C4: =Assumptions!C17 -> 4 | D4: =Assumptions!D17 -> 6 | E4: =Assumptions!E17 -> 9 | F4: =Assumptions!F17 -> 12 | G4: =Assumptions!G17 -> 15
A5: Price per cup | C5: =Assumptions!$B$4*(1+Assumptions!$B$7)^(C$3-$C$3) -> 4.6 | D5: =Assumptions!$B$4*(1+Assumptions!$B$7)^(D$3-$C$3) -> 4.738 | E5: =Assumptions!$B$4*(1+Assumptions!$B$7)^(E$3-$C$3) -> 4.88014 | F5: =Assumptions!$B$4*(1+Assumptions!$B$7)^(F$3-$C$3) -> 5.0265442 | G5: =Assumptions!$B$4*(1+Assumptions!$B$7)^(G$3-$C$3) -> 5.1773405
A6: Cups sold | C6: =C4*Assumptions!$B$5*Assumptions!$B$6 -> 446400 | D6: =D4*Assumptions!$B$5*Assumptions!$B$6 -> 669600 | E6: =E4*Assumptions!$B$5*Assumptions!$B$6 -> 1004400 | F6: =F4*Assumptions!$B$5*Assumptions!$B$6 -> 1339200 | G6: =G4*Assumptions!$B$5*Assumptions!$B$6 -> 1674000
A7: Revenue | C7: =C5*C6 -> 2053440 | D7: =D5*D6 -> 3172564.8 | E7: =E5*E6 -> 4901612.6 | F7: =F5*F6 -> 6731548 | G7: =G5*G6 -> 8666868

Sheet Costs
A1: Costs
C3: =Revenue!C3 -> 2027 | D3: =Revenue!D3 -> 2028 | E3: =Revenue!E3 -> 2029 | F3: =Revenue!F3 -> 2030 | G3: =Revenue!G3 -> 2031
A4: Cost of goods | C4: =Revenue!C7*Assumptions!$B$8 -> 636566.4 | D4: =Revenue!D7*Assumptions!$B$8 -> 983495.09 | E4: =Revenue!E7*Assumptions!$B$8 -> 1519499.9 | F4: =Revenue!F7*Assumptions!$B$8 -> 2086779.9 | G4: =Revenue!G7*Assumptions!$B$8 -> 2686729.1
A5: Rent | C5: =Revenue!C4*Assumptions!$B$9 -> 336000 | D5: =Revenue!D4*Assumptions!$B$9 -> 504000 | E5: =Revenue!E4*Assumptions!$B$9 -> 756000 | F5: =Revenue!F4*Assumptions!$B$9 -> 1008000 | G5: =Revenue!G4*Assumptions!$B$9 -> 1260000
A6: Staff | C6: =Revenue!C4*Assumptions!$B$10*Assumptions!$B$11 -> 912000 | D6: =Revenue!D4*Assumptions!$B$10*Assumptions!$B$11 -> 1368000 | E6: =Revenue!E4*Assumptions!$B$10*Assumptions!$B$11 -> 2052000 | F6: 2280000 | G6: =Revenue!G4*Assumptions!$B$10*Assumptions!$B$11 -> 3420000
A7: Marketing | C7: =Revenue!C7*0.04 -> 82137.6 | D7: =Revenue!D7*0.04 -> 126902.59 | E7: =Revenue!E7*0.04 -> 196064.5 | F7: =Revenue!F7*0.04 -> 269261.92 | G7: =Revenue!G7*0.04 -> 346674.72
A8: New store openings | C8: =Revenue!C4*Assumptions!$B$13 -> 1000000 | D8: =(Revenue!D4-Revenue!C4)*Assumptions!$B$13 -> 500000 | E8: =(Revenue!E4-Revenue!D4)*Assumptions!$B$13 -> 750000 | F8: =(Revenue!F4-Revenue!E4)*Assumptions!$B$13 -> 750000 | G8: =(Revenue!G4-Revenue!F4)*Assumptions!$B$13 -> 750000
A9: Total costs | C9: =SUM(C4:C8) -> 2966704 | D9: =SUM(D4:D8) -> 3482397.7 | E9: =SUM(E4:E8) -> 5273564.4 | F9: =SUM(F4:F8) -> 6394041.8 | G9: =SUM(G4:G8) -> 8463403.8

Sheet P&L
A1: Profit and loss
C3: =Revenue!C3 -> 2027 | D3: =Revenue!D3 -> 2028 | E3: =Revenue!E3 -> 2029 | F3: =Revenue!F3 -> 2030 | G3: =Revenue!G3 -> 2031 | H3: 5-year total
A4: Revenue | C4: =Revenue!C7 -> 2053440 | D4: =Revenue!D7 -> 3172564.8 | E4: =Revenue!E7 -> 4901612.6 | F4: =Revenue!F7 -> 6731548 | G4: =Revenue!G7 -> 8666868 | H4: =SUM(C4:G4) -> 25526033
A5: Total costs | C5: =Costs!C9 -> 2966704 | D5: =Costs!D9 -> 3482397.7 | E5: =Costs!E9 -> 5273564.4 | F5: =Costs!F9 -> 6394041.8 | G5: =Costs!G9 -> 8463403.8 | H5: =SUM(C5:G5) -> 26580112
A6: Profit before tax | C6: =C4-C5 -> -913264 | D6: =D4-D5 -> -309832.88 | E6: =E4-E5 -> -371951.8 | F6: =F4-F5 -> 337506.2 | G6: =G4-G5 -> 203464.23 | H6: =SUM(C6:G6) -> -1054078.3
A7: Tax | C7: =MAX(0,C6*TaxRate) -> 0 | D7: =MAX(0,D6*TaxRate) -> 0 | E7: =MAX(0,E6*TaxRate) -> 0 | F7: =MAX(0,F6*TaxRate) -> 84376.549 | G7: =MAX(0,G6*TaxRate) -> 50866.057 | H7: =SUM(C7:G7) -> 135242.61
A8: Net profit | C8: =C6-C7 -> -913264 | D8: =D6-D7 -> -309832.88 | E8: =E6-E7 -> -371951.8 | F8: =F6-F7 -> 253129.65 | G8: =G6-G7 -> 152598.17 | H8: =SUM(C8:F8) -> -1341919
A10: Net margin | C10: =IFERROR(C8/C4,0) -> -0.44474832 | D10: =IFERROR(D8/D4,0) -> -0.097660064 | E10: =IFERROR(E8/E4,0) -> -0.075883557 | F10: =IFERROR(F8/F4,0) -> 0.037603482 | G10: =IFERROR(G8/G4,0) -> 0.017607072

Sheet Dashboard
A1: Northwind Coffee: plan at a glance
A3: 5-year revenue | B3: ='P&L'!H4 -> 25526033
A4: 5-year net profit | B4: ='P&L'!H8 -> -1341919
A5: Stores by 2031 | B5: =Revenue!G4 -> 15
A6: Best year for profit | B6: =INDEX('P&L'!C3:G3,MATCH(MAX('P&L'!C8:G8),'P&L'!C8:G8,0)) -> 2030
A7: Average net margin | B7: =AVERAGE('P&L'!C10:G10) -> -0.11261628
A8: Verdict | B8: =IF(B4>0,"Profitable over 5 years","Loses money") -> Loses money
A9: Cash buffer needed | B9: =Scratch!B4 -> 741676

Sheet Scratch
A1: old workings, do not use
A3: Buffer months | B3: 3
A4: Buffer | B4: =B3*Costs!C9/12 -> 741676
A6: Old FX rate | B6: =#REF!*1.1 -> #REF!
